{"textListData":{"headerTitle":"Select a recipe","headerSubtitle":"here are some recipes we found using your ingredients","headerAttributionImage":"","backgroundImageSource":"https://i.imgur.com/BMb0Emf.png","listItemsToShow":[{"primaryText":"Recipe1","secondaryText":"cooking time and serving size","secondaryTextPosition":"bottom","tertiaryText":"num ingredients used","tertiaryTextPosition":"bottom","imageThumbnailSource":"https://d2o906d8ln7ui1.cloudfront.net/images/md_brie.png","hideOrdinal":true,"touchForward":true},{"primaryText":"Recipe2","secondaryText":"cooking time and serving size","secondaryTextPosition":"bottom","tertiaryText":"num ingredients used","tertiaryTextPosition":"bottom","imageThumbnailSource":"https://d2o906d8ln7ui1.cloudfront.net/images/md_brie.png","hideOrdinal":true,"touchForward":true}]}}